MANIFEST.in
setup.py
sbswebsite.egg-info/PKG-INFO
sbswebsite.egg-info/SOURCES.txt
sbswebsite.egg-info/dependency_links.txt
sbswebsite.egg-info/entry_points.txt
sbswebsite.egg-info/requires.txt
sbswebsite.egg-info/top_level.txt
templates/test.html
website/__init__.py
website/add_env_var.py
website/update_config.py
website/views.py
website/static/css/style.css
website/templates/base.html
website/templates/combined_base.html
website/templates/combined_pages.html
website/templates/contact.html
website/templates/home.html
website/templates/personal.html
website/templates/professional.html
website/templates/test.html